LICENSE
MANIFEST.in
README.rst
buildout.cfg
develop.cfg
pyproject.toml
requirements.txt
setup.py
version.txt
bob/__init__.py
bob.sp.egg-info/PKG-INFO
bob.sp.egg-info/SOURCES.txt
bob.sp.egg-info/dependency_links.txt
bob.sp.egg-info/not-zip-safe
bob.sp.egg-info/requires.txt
bob.sp.egg-info/top_level.txt
bob/sp/__init__.py
bob/sp/dct.cpp
bob/sp/dct1d.cpp
bob/sp/dct2d.cpp
bob/sp/extrapolate.cpp
bob/sp/fft.cpp
bob/sp/fft1d.cpp
bob/sp/fft2d.cpp
bob/sp/idct1d.cpp
bob/sp/idct2d.cpp
bob/sp/ifft1d.cpp
bob/sp/ifft2d.cpp
bob/sp/main.cpp
bob/sp/quantization.cpp
bob/sp/test_extrapolate.py
bob/sp/test_fft_dct.py
bob/sp/test_quantization.py
bob/sp/version.cpp
bob/sp/cpp/DCT1D.cpp
bob/sp/cpp/DCT1DNaive.cpp
bob/sp/cpp/DCT2D.cpp
bob/sp/cpp/DCT2DNaive.cpp
bob/sp/cpp/FFT1D.cpp
bob/sp/cpp/FFT1DNaive.cpp
bob/sp/cpp/FFT2D.cpp
bob/sp/cpp/FFT2DNaive.cpp
bob/sp/cpp/fftpack.c
bob/sp/include/bob.sp/DCT1D.h
bob/sp/include/bob.sp/DCT1DNaive.h
bob/sp/include/bob.sp/DCT2D.h
bob/sp/include/bob.sp/DCT2DNaive.h
bob/sp/include/bob.sp/FFT1D.h
bob/sp/include/bob.sp/FFT1DNaive.h
bob/sp/include/bob.sp/FFT2D.h
bob/sp/include/bob.sp/FFT2DNaive.h
bob/sp/include/bob.sp/Quantization.h
bob/sp/include/bob.sp/api.h
bob/sp/include/bob.sp/config.h
bob/sp/include/bob.sp/conv.h
bob/sp/include/bob.sp/extrapolate.h
bob/sp/include/bob.sp/fftpack.h
bob/sp/include/bob.sp/fftshift.h
bob/sp/include/bob.sp/interpolate.h
doc/c_cpp_api.rst
doc/conf.py
doc/index.rst
doc/links.rst
doc/py_api.rst